MANIFEST.in
requirements.txt
setup.cfg
setup.py
zendesk/__init__.py
zendesk/create_new_post_shell.py
zendesk/deploy.py
zendesk/track_changes.py
zendesk/scripts/__init__.py
zendesk/scripts/cloudfront_images.py
zendesk/scripts/compare_repos.py
zendesk/scripts/file_constants.py
zendesk/scripts/renderer.py
zendesk/scripts/startup_changes.py
zendesk/scripts/timing.py
zendesk_help_center_backer.egg-info/PKG-INFO
zendesk_help_center_backer.egg-info/SOURCES.txt
zendesk_help_center_backer.egg-info/dependency_links.txt
zendesk_help_center_backer.egg-info/entry_points.txt
zendesk_help_center_backer.egg-info/requires.txt
zendesk_help_center_backer.egg-info/top_level.txt