Metadata-Version: 1.1
Name: zendesk-help-center-backer
Version: 0.2
Summary: A Zendesk help center backer written in Python
Home-page: https://github.com/aerofs/zendesk-help-center-backer
Author: AeroFS
Author-email: oss@aerofs.com
License: UNKNOWN
Keywords: zendesk,solution,help center,knowledge base
Platform: UNKNOWN
Classifier: Development Status :: 3 - Alpha
Classifier: Intended Audience :: Developers
Classifier: License :: OSI Approved :: MIT License
Classifier: Natural Language :: English
Classifier: Programming Language :: Python
Classifier: Topic :: Software Development
